lazytrainer/__init__.py
lazytrainer/trainer.py
lazytrainer-0.1.3.dist-info/METADATA
lazytrainer-0.1.3.dist-info/WHEEL
lazytrainer-0.1.3.dist-info/top_level.txt
lazytrainer-0.1.3.dist-info/RECORD
