Metadata-Version: 2.1
Name: lazytrainer
Version: 0.1.3
Summary: Lazy ML: Because training models shouldn't need more energy than your morning coffee.
Author: Mr. Phantom
Classifier: Programming Language :: Python :: 3
Classifier: License :: OSI Approved :: MIT License
Requires-Python: >=3.7
Requires-Dist: pandas
Requires-Dist: numpy
Requires-Dist: scikit-learn
Requires-Dist: matplotlib
Requires-Dist: joblib
Requires-Dist: tqdm
